mcp_plus/__init__.py
mcp_plus/__main__.py
mcp_plus/server_impl.py
generate_brand_ad_cover-0.1.5.dist-info/METADATA
generate_brand_ad_cover-0.1.5.dist-info/WHEEL
generate_brand_ad_cover-0.1.5.dist-info/entry_points.txt
generate_brand_ad_cover-0.1.5.dist-info/RECORD
