Metadata-Version: 2.4
Name: generate-brand-ad-cover
Version: 0.1.5
Summary: 生成品牌广告封面 - MCP服务器，支持多种风格的品牌广告封面生成
Project-URL: Homepage, https://github.com/shidianxiaoerya/generate-brand-ad-cover
Project-URL: Repository, https://github.com/shidianxiaoerya/generate-brand-ad-cover
Project-URL: Issues, https://github.com/shidianxiaoerya/generate-brand-ad-cover/issues
Author-email: shidianxiaoerya <934679045@qq.com>
License: MIT
Keywords: advertisement,brand,cover,design,generator,mcp,svg
Classifier: Development Status :: 4 - Beta
Classifier: Intended Audience :: Developers
Classifier: License :: OSI Approved :: MIT License
Classifier: Programming Language :: Python :: 3
Classifier: Programming Language :: Python :: 3.8
Classifier: Programming Language :: Python :: 3.9
Classifier: Programming Language :: Python :: 3.10
Classifier: Programming Language :: Python :: 3.11
Classifier: Programming Language :: Python :: 3.12
Classifier: Programming Language :: Python :: 3.13
Classifier: Topic :: Multimedia :: Graphics :: Graphics Conversion
Classifier: Topic :: Software Development :: Libraries :: Python Modules
Requires-Python: >=3.8
Requires-Dist: mcp[cli]>=1.12.4
